MANIFEST.in
README.rst
setup.py
docs/HISTORY.txt
docs/LICENSE.GPL
docs/LICENSE.txt
ftw/__init__.py
ftw.notification.email.egg-info/PKG-INFO
ftw.notification.email.egg-info/SOURCES.txt
ftw.notification.email.egg-info/dependency_links.txt
ftw.notification.email.egg-info/entry_points.txt
ftw.notification.email.egg-info/namespace_packages.txt
ftw.notification.email.egg-info/not-zip-safe
ftw.notification.email.egg-info/requires.txt
ftw.notification.email.egg-info/top_level.txt
ftw/notification/__init__.py
ftw/notification/email/__init__.py
ftw/notification/email/adapters.py
ftw/notification/email/composer.py
ftw/notification/email/configure.zcml
ftw/notification/email/interfaces.py
ftw/notification/email/notifier.py
ftw/notification/email/testing.py
ftw/notification/email/activity/__init__.py
ftw/notification/email/activity/configure.zcml
ftw/notification/email/activity/renderer.py
ftw/notification/email/activity/subscribers.py
ftw/notification/email/activity/templates/notification.pt
ftw/notification/email/events/__init__.py
ftw/notification/email/events/handlers.py
ftw/notification/email/locales/ftw.activity.pot
ftw/notification/email/locales/ftw.notification.email-manual.pot
ftw/notification/email/locales/ftw.notification.email.pot
ftw/notification/email/locales/de/LC_MESSAGES/ftw.activity.po
ftw/notification/email/locales/de/LC_MESSAGES/ftw.notification.email.po
ftw/notification/email/locales/en/LC_MESSAGES/ftw.activity.po
ftw/notification/email/locales/en/LC_MESSAGES/ftw.notification.email.po
ftw/notification/email/locales/fr/LC_MESSAGES/ftw.notification.email.po
ftw/notification/email/profiles/default/metadata.xml
ftw/notification/email/profiles/default/propertiestool.xml
ftw/notification/email/templates/__init__.py
ftw/notification/email/templates/base.pt
ftw/notification/email/templates/base.py
ftw/notification/email/templates/composer-html.pt
ftw/notification/email/tests/__init__.py
ftw/notification/email/tests/test_activity.py
ftw/notification/email/tests/test_events.py
ftw/notification/email/tests/test_format_email.py