Metadata-Version: 1.1
Name: ftw.notification.email
Version: 2.1.0
Summary: Send edit-notifications by email.
Home-page: https://github.com/4teamwork/ftw.notification.email
Author: Jonas Baumann
Author-email: mailto:info@4teamwork.ch
License: GPL2
Keywords: ftw notification email plone
Platform: UNKNOWN
Classifier: Framework :: Plone
Classifier: Framework :: Plone :: 4.3
Classifier: Programming Language :: Python
Classifier: Topic :: Software Development :: Libraries :: Python Modules
